[
    {
      "title": "HTML",
      "imageSrc": "src/data/html.png"
    },
    {
      "title": "CSS",
      "imageSrc": "skills/css.png"
    },
    {
      "title": "React",
      "imageSrc": "skills/react.png"
    },
    {
      "title": "Node",
      "imageSrc": "skills/node.png"
    },
    {
      "title": "Python",
      "imageSrc": "assets/python.svg"
    },
    {
      "title": "Java",
      "imageSrc": "skills/mongodb.png"
    },
    {
      "title": "Figma",
      "imageSrc": "assets/figma.svg"
    },
    {
      "title": "JavaScript",
      "imageSrc": "skills/javascript.png"
    },
    {
      "title": "C",
      "imageSrc": "skills/graphql.png"
    },
    {
      "title": "SQl",
      "imageSrc": "skills/mongodb.png"
    }
  ]